{
  "_fv": 57,
  "_type": "tool",
  "definition": {
    "toolType": "Spade",
    "renderType": 0,
    "blockingRenderType": 0,
    "texture": "cybershovel",
    "customModelName": "Normal",
    "blockingModelName": "Normal blocking",
    "name": "Enderium Shovel",
    "specialInformation": {
      "fixedValue": []
    },
    "creativeTab": {
      "value": "CUSTOM:ShinyCreepersEndUpdate"
    },
    "harvestLevel": 5,
    "efficiency": 10.0,
    "attackSpeed": 1.0,
    "enchantability": 20,
    "damageVsEntity": 7.5,
    "usageCount": 2501,
    "blocksAffected": [],
    "repairItems": [
      {
        "value": "CUSTOM:EnderiteIngot"
      }
    ],
    "immuneToFire": false,
    "stayInGridWhenCrafting": false,
    "damageOnCrafting": false
  }
}